ropemacs/__init__.py
ropemacs-0.8.dist-info/top_level.txt
ropemacs-0.8.dist-info/METADATA
ropemacs-0.8.dist-info/DESCRIPTION.rst
ropemacs-0.8.dist-info/metadata.json
ropemacs-0.8.dist-info/WHEEL
ropemacs-0.8.dist-info/RECORD
