Metadata-Version: 1.1
Name: ropemacs
Version: 0.8
Summary: An emacs mode for using rope python refactoring library
Home-page: http://rope.sf.net/ropemacs.html
Author: Ali Gholami Rudi
Author-email: aligrudi@users.sourceforge.net
License: GNU GPL
Platform: UNKNOWN
Classifier: Development Status :: 4 - Beta
Classifier: Operating System :: OS Independent
Classifier: Environment :: X11 Applications
Classifier: Environment :: Win32 (MS Windows)
Classifier: Environment :: MacOS X
Classifier: Intended Audience :: Developers
Classifier: License :: OSI Approved :: GNU General Public License (GPL)
Classifier: Natural Language :: English
Classifier: Programming Language :: Python
Classifier: Topic :: Text Editors :: Emacs
Classifier: Topic :: Software Development
Requires: ropemode
